quickbytes/__init__.py
quickbytes/core.py
quickbytes/io.py
quickbytes-0.1.1.dist-info/METADATA
quickbytes-0.1.1.dist-info/WHEEL
quickbytes-0.1.1.dist-info/top_level.txt
quickbytes-0.1.1.dist-info/RECORD
