Metadata-Version: 2.1
Name: quickbytes
Version: 0.1.1
Summary: A lightweight data manipulation library like pandas
Home-page: https://github.com/yourusername/bytes
Author: senthil kumar
Author-email: u.senthilkumar1@gmail.com
Requires-Python: >=3.6
